pyarcade/__init__.py
pyarcade/api/__init__.py
pyarcade/api/client.py
pyarcade/api/config.py
pyarcade/api/sync.py
pyarcade/dao/__init__.py
pyarcade/dao/database.py
pyarcade/model/__init__.py
pyarcade/model/database.py
pyarcade/model/request.py
tests/__init__.py
tests/api/__init__.py
tests/api/test_client.py
tests/api/test_config.py
tests/model/__init__.py
tests/model/test_request.py
pyarcade-0.0.1.dist-info/LICENSE
pyarcade-0.0.1.dist-info/METADATA
pyarcade-0.0.1.dist-info/WHEEL
pyarcade-0.0.1.dist-info/top_level.txt
pyarcade-0.0.1.dist-info/RECORD
